{
  "source": "https://www.hangon.co.kr/credit-balance",
  "history_source": "https://finance.naver.com/sise/sise_deposit.naver",
  "updated_at": "2026-07-17T11:55:36.874672+00:00",
  "unit": "trillion_krw",
  "range": "latest_6_calendar_months",
  "collection_mode": "snapshot_append",
  "message": "Hang on 최신 검증값을 날짜별로 누적했습니다.",
  "fallback_reason": "Hang on 전체 시계열 후보를 찾지 못함 / 보조 시계열 실패: page 1: 대상 표 없음",
  "verified_against": {
    "date": "2026-07-14",
    "ratio": 30.7278,
    "credit_trillion": 34.2,
    "deposit_trillion": 111.3
  },
  "latest": {
    "date": "2026-07-14",
    "credit_trillion": 34.2,
    "deposit_trillion": 111.3,
    "ratio": 30.7278
  },
  "series": [
    {
      "date": "2026-07-08",
      "credit_trillion": 36.6,
      "deposit_trillion": 110.9,
      "ratio": 33.0027
    },
    {
      "date": "2026-07-09",
      "credit_trillion": 36.1,
      "deposit_trillion": 107.1,
      "ratio": 33.7068
    },
    {
      "date": "2026-07-10",
      "credit_trillion": 35.0,
      "deposit_trillion": 105.6,
      "ratio": 33.1439
    },
    {
      "date": "2026-07-13",
      "credit_trillion": 34.3,
      "deposit_trillion": 109.0,
      "ratio": 31.4679
    },
    {
      "date": "2026-07-14",
      "credit_trillion": 34.2,
      "deposit_trillion": 111.3,
      "ratio": 30.7278
    }
  ]
}